[
  {
    "file": "about.html",
    "route": "/about",
    "label": "About",
    "seoTitle": "Find Top Talent for Your Business with Code Recruitment",
    "seoDescription": "Discover top talent with code. - a leading recruitment agency in the US, specializing in connecting innovative companies with skilled professionals for growth.",
    "visibleText": "Find Top Talent for Your Business with Code Recruitment code. Team Meetups About Blog Our Services About Code Talent Great people make great companies. At Code Talent, we specialize in talent acquisition for modern technology companies — from early-stage startups to billion-dollar pre-IPO unicorns. Based in Denver, CO 🏔️, we connect exceptional talent with innovative companies across the country. Our Mission 🎯 We aim to be a true partner within the Colorado entrepreneurial community. Our mission is to support growing companies by providing top-tier recruitment services and building meaningful relationships. With deep community involvement and real-time market insights, we help our clients build the best teams possible. What Sets Us Apart ✨ 1) Talent-First Approach 👤 We put people first. We know how important career decisions are and strive to deliver a communicative, transparent, and trustworthy experience that builds long-lasting relationships. 2) Community Involvement 🏙️ Code Talent was built on giving back. We’ve supported the Colorado tech community since our founding — hosting meetups, mentoring founders, and co-chairing Denver Startup Week’s Product and Developer tracks since 2013. Meetups we've supported: 🔩 AI Tinkerers 🐍 Denver Python Meetup 🚀 MLOps Meetup 💁‍♀️ Women in Product 🐿️ Mile High Gophers (Golang Meetup) ⚙️ Denver Microservices Meetup ☀️ Denverscript Meetup ￼ React Meetup 🍎 CocoaHeads Meetup 🏔️ API Denver ↗️ Denver Leadership Meetup 🌲 Colorado Product Foundation 👀 Paired Community 💡 Black Tech Denver 🧪 Denver Elixir Meetup 3) Experience & Representation 🧠 Our team brings experience as service providers, community builders, and operators across the startup ecosystem. We act as an extension of your brand 🔗, helping you tell your story while delivering great outcomes for clients and candidates alike. 4) Flexible Fee Structure 💸 Hiring is hard enough. We offer a contingency-based, flexible pricing model — meaning you only pay if we deliver 👌. This allows you to spend your time on the higher-value work of building your company. Industries We Support 🌐 We support a broad range of sectors, including: 🌱 Clean / Green Energy 🧬 HealthTech / Healthcare 🤖 Artificial Intelligence 🚀 Aerospace 🌎 Climate Tech 📶 Telecommunication 👨‍🏫 EdTech / Education 🧩 B-Corporations 🛠️ SaaS 📡 Internet of Things (IoT) Company Stages We Serve 📈 Over the past decade, we’ve partnered with hundreds of companies — from early-stage to enterprise. These include: 🌱 Seed & Pre-Seed Startups ⚡ Hyper-Growth Mid & Late Stage 💼 Post-IPO Companies 🏢 Private Equity Firms 🏛️ Enterprise Organizations Roles We Specialize In 🧑‍💻 We help companies hire top talent across engineering, product, and design — from individual contributors to executive leaders: 🖥️ Engineering: Frontend, Backend, Full-Stack, Platform, Mobile 🧑‍🏫 Engineering Leadership: Managers, Directors, CTOs 📊 Data: Data Science, Data Engineering, BI, Analytics 🛠️ Infrastructure: DevOps, Automation, Platform ✅ QA: Manual & Automated Testing 📌 Product: PMs, Directors, Chief Product Officers 🎨 UI/UX: Product Designers, Visual Designers, UX Writers 🏢 Enterprise Software:Salesforce Ecosystem 🧾 Finance & Accounting 🛎️ Customer Success 📣 Sales & Marketing ⚙️ Operations Great Companies We've Partnered With 🤝 We’re proud to have worked with many great teams, including: 🎓 Guild Education 💰 Ibotta 🦄 MagicSchool 🎶 Beatport 💡 UpLight 🕵️ GoSpotCheck 💬 CirrusMD ☀️ Wunder Capital 🧠 Notion 📦 Brandfolder And many more... Join Our Community 💬 We’re committed to giving back to the Colorado tech scene. Our network, track record, and trusted approach have helped build teams — and careers — that make a difference. 👉 Get in touch with us to learn more about how we can help you scale your team or take your next career step.",
    "blockText": [
      "About Code Talent Great people make great companies. At Code Talent, we specialize in talent acquisition for modern technology companies — from early-stage startups to billion-dollar pre-IPO unicorns. Based in Denver, CO 🏔️, we connect exceptional talent with innovative companies across the country. Our Mission 🎯 We aim to be a true partner within the Colorado entrepreneurial community. Our mission is to support growing companies by providing top-tier recruitment services and building meaningful relationships. With deep community involvement and real-time market insights, we help our clients build the best teams possible. What Sets Us Apart ✨ 1) Talent-First Approach 👤 We put people first. We know how important career decisions are and strive to deliver a communicative, transparent, and trustworthy experience that builds long-lasting relationships. 2) Community Involvement 🏙️ Code Talent was built on giving back. We’ve supported the Colorado tech community since our founding — hosting meetups, mentoring founders, and co-chairing Denver Startup Week’s Product and Developer tracks since 2013. Meetups we've supported: 🔩 AI Tinkerers 🐍 Denver Python Meetup 🚀 MLOps Meetup 💁‍♀️ Women in Product 🐿️ Mile High Gophers (Golang Meetup) ⚙️ Denver Microservices Meetup ☀️ Denverscript Meetup ￼ React Meetup 🍎 CocoaHeads Meetup 🏔️ API Denver ↗️ Denver Leadership Meetup 🌲 Colorado Product Foundation 👀 Paired Community 💡 Black Tech Denver 🧪 Denver Elixir Meetup 3) Experience & Representation 🧠 Our team brings experience as service providers, community builders, and operators across the startup ecosystem. We act as an extension of your brand 🔗, helping you tell your story while delivering great outcomes for clients and candidates alike. 4) Flexible Fee Structure 💸 Hiring is hard enough. We offer a contingency-based, flexible pricing model — meaning you only pay if we deliver 👌. This allows you to spend your time on the higher-value work of building your company. Industries We Support 🌐 We support a broad range of sectors, including: 🌱 Clean / Green Energy 🧬 HealthTech / Healthcare 🤖 Artificial Intelligence 🚀 Aerospace 🌎 Climate Tech 📶 Telecommunication 👨‍🏫 EdTech / Education 🧩 B-Corporations 🛠️ SaaS 📡 Internet of Things (IoT) Company Stages We Serve 📈 Over the past decade, we’ve partnered with hundreds of companies — from early-stage to enterprise. These include: 🌱 Seed & Pre-Seed Startups ⚡ Hyper-Growth Mid & Late Stage 💼 Post-IPO Companies 🏢 Private Equity Firms 🏛️ Enterprise Organizations Roles We Specialize In 🧑‍💻 We help companies hire top talent across engineering, product, and design — from individual contributors to executive leaders: 🖥️ Engineering: Frontend, Backend, Full-Stack, Platform, Mobile 🧑‍🏫 Engineering Leadership: Managers, Directors, CTOs 📊 Data: Data Science, Data Engineering, BI, Analytics 🛠️ Infrastructure: DevOps, Automation, Platform ✅ QA: Manual & Automated Testing 📌 Product: PMs, Directors, Chief Product Officers 🎨 UI/UX: Product Designers, Visual Designers, UX Writers 🏢 Enterprise Software:Salesforce Ecosystem 🧾 Finance & Accounting 🛎️ Customer Success 📣 Sales & Marketing ⚙️ Operations Great Companies We've Partnered With 🤝 We’re proud to have worked with many great teams, including: 🎓 Guild Education 💰 Ibotta 🦄 MagicSchool 🎶 Beatport 💡 UpLight 🕵️ GoSpotCheck 💬 CirrusMD ☀️ Wunder Capital 🧠 Notion 📦 Brandfolder And many more... Join Our Community 💬 We’re committed to giving back to the Colorado tech scene. Our network, track record, and trusted approach have helped build teams — and careers — that make a difference. 👉 Get in touch with us to learn more about how we can help you scale your team or take your next career step."
    ]
  },
  {
    "file": "blog.html",
    "route": "/blog",
    "label": "Blog",
    "seoTitle": "Finding Your Dream Job: Code's Recruitment Expertise",
    "seoDescription": "Discover top talent with code., the leading recruitment agency in the US. We connect businesses with skilled professionals to elevate your workforce success.",
    "visibleText": "Finding Your Dream Job: Code's Recruitment Expertise code. Team Meetups About Blog Our Services Blog First Call, Big Stakes: How to Nail Your Initial Interview Interview Prep Guide for Software Engineers code. built with ❤️ in denver, co Contact About Privacy Policy",
    "blockText": []
  },
  {
    "file": "blog__first-call--big-stakes--how-to-nail-your-initial-interview.html",
    "route": "/blog/first-call--big-stakes--how-to-nail-your-initial-interview",
    "label": "first-call--big-stakes--how-to-nail-your-initial-interview",
    "seoTitle": "First Call, Big Stakes: How to Nail Your Initial Interview",
    "seoDescription": "It may sound cliche, but when it comes to the initial discussion for a new role, you really do get one chance to make a great first impression. You'd be su",
    "visibleText": "First Call, Big Stakes: How to Nail Your Initial Interview code. Team Meetups About Blog Our Services First Call, Big Stakes: How to Nail Your Initial Interview Jun 19, 2025 · By Conor Swanson It may sound cliche, but when it comes to the initial discussion for a new role, you really do get one chance to make a great first impression. You'd be surprised how often we see impressive candidates miss easy-to-avoid obstacles that end up costing them a chance to further explore a role. Whether it’s with a recruiter, internal talent partner, or hiring manager, the initial interview is make-or-break. It’s your shot to show you're not just a good resume—you're a real human who fits the role, the team, and the culture. And especially in the startup world, where every hire matters, getting this conversation right is critical. Here’s the good news: with a little prep, you can walk in with confidence and make a strong first impression.&nbsp; 🔎 Start with Real Company Research Don’t just skim the homepage and call it good. Learn the basics, but go deeper: + What problem is the company solving? + Who are their customers? +Any recent fundraising? Press coverage? Product launches? Check out the company blog (great for understanding tone and focus), and browse their LinkedIn page/posts to get an understanding for the company size, key team members, recent media they've highlighted, etc. Tools like Crunchbase or TechCrunch can help you dig into funding history and major announcements. Bonus points: Look up your interviewer on LinkedIn. Knowing their role, background, and even tenure at the company helps humanize the conversation and gives you a clearer sense of their perspective. It also may provide some relevant insight into questions you can target in the discussion.&nbsp; 🧐 Understand the Role—Not Just the Title Read the job description again—closely. What are the real priorities of the role? Is it heavy technical depth? Cross-functional collaboration? Ownership of a greenfield build? Do they mention specific values for their organization? Compare the job description to your own experience and prep examples that speak directly to their needs. Think in terms of: + Scope of your past work + Measurable impact + Tools/technologies you've worked with + Environments where you thrived (especially fast-paced or ambiguous ones) + Examples from your own experience that map or highlight key company values Startup teams don’t have time to connect the dots for you—come in ready to do that for them. ✅ Anticipate the Core Themes These early conversations usually aim to assess: 1) High-level technical or functional fit 2) Alignment with company values and mission 3) Ability to operate in a startup environment 4) Genuine interest in the business Be ready to speak to all four. And yes, behavioral questions can absolutely pop up even in a “casual” intro call. Don’t get caught flat-footed. Have a few strong stories ready that show: + A hard problem you solved + A big win you’re proud of + A time you failed and what you learned + Something you’re actively working to improve Here’s a great prep resource if you want to brush up: Using the STAR method for your next behavioral interview 30+ Behavioral Interview Questions to Prep For (With Sample Answers!)&nbsp; 💻 Be Ready to Walk Through Your Career Especially with hiring managers, you may be asked to walk through your job history. Be specific—this isn’t the time to rattle off titles and responsibilities. Highlight ownership and outcomes. If you launched a product, rewrote a system, reduced latency, or led a migration—say it. Quantify it when you can. The key is showing how you drove value in your past roles. That’s what separates a good candidate from a great one. 🤝 Treat the Interview Like a Real Meeting (Because It Is!) This may seem basic, but you'd be surprised how many great candidates lose momentum because of poor presentation. Be thoughtful about how you show up: + Double check your tech: Make sure Zoom (or whatever platform they’re using) is up to date, your camera works, and your mic isn’t cutting in and out. Do a quick test call with a friend if you haven’t used it recently. + Set the scene: Avoid taking the call from your car, a noisy café, or your kitchen while making lunch. Quiet, clean, and neutral background is ideal. + Dress appropriately: No need for a suit—but don’t look like you just rolled out of bed either. Even for remote-first companies, presentation still matters. + Bring the energy: These calls are short. A little enthusiasm goes a long way. It’s okay to be nervous, but aim for clear, present, and engaged. This is one of those things that’s easy to get right with a bit of planning—and it shows respect for the interviewer’s time. 🙋 Come With Questions That Show You’re In It You’ll often get a few minutes at the end to ask questions—don’t waste them on things you could have Googled. Ask what success looks like in the role. Ask about team structure, engineering culture, product roadmap, or how decisions get made. Show them you’re evaluating them too—and that you’re excited about the opportunity. A few ideas to get you started: + What are the biggest challenges the team is currently facing? + How does the company define success in this role over the next 6–12 months? + What are the traits of someone who’s thrived here? Here’s another resource worth skimming: Questions to Ask During a Startup Interview 📱 Final Thought: Don’t Phone It In Even if this feels like a “screen,” treat it like the real deal. First impressions stick. Startups are fast-moving, and if you click with the first person you speak with, it could accelerate the whole process. Show up sharp, prepared, curious, and genuinely interested. And if you’re working with a recruiter (like us), lean on them. We know the companies, we know the hiring teams, and we can help you prep. That’s part of our job. code. built with ❤️ in denver, co Contact About Privacy Policy",
    "blockText": []
  },
  {
    "file": "blog__interview-prep-guide-for-software-engineers.html",
    "route": "/blog/interview-prep-guide-for-software-engineers",
    "label": "interview-prep-guide-for-software-engineers",
    "seoTitle": "Interview Prep Guide for Software Engineers",
    "seoDescription": "Riley here! 🙋‍♀️  I’ve been a full desk technical recruiter for nearly 10 years. Most of my time has been spent as an agency recruiter with Code Talent, b",
    "visibleText": "Interview Prep Guide for Software Engineers code. Team Meetups About Blog Our Services Interview Prep Guide for Software Engineers May 08, 2023 · By Riley Scardina Riley here! 🙋‍♀️ I’ve been a full desk technical recruiter for nearly 10 years. Most of my time has been spent as an agency recruiter with Code Talent, but I also have a year of internal recruiting experience on Twitter’s Revenue Platform team. I’ve created this guide by drawing on my exposure to both big tech and startup hiring. A Quick Note📝: This interview prep guide is primarily designed for software engineering positions, although it may be helpful for other roles within the tech industry. I’d like to flag that the advice provided is based on my personal opinions and experience, and should not be considered an endorsement of the hiring processes used in big tech, or by companies emulating big tech hiring. Rather, it is intended to provide guidance on how to navigate the \"industry standard\" interview process and improve your chances of success. I have lots of feels around this, but that is neither here nor there. TLDR: don’t hate the player, hate the game 😉 Knowledge is Power 💡 More often than not, a job description is designed or reviewed directly by the hiring manager and your potential boss. It’s a good idea to thoroughly research the company's values and the position (required skills, experience, and \"nice to haves\"). I can’t tell you how many candidates I’ve seen eliminated for lack of company knowledge. A company most often will have a “values” page (I’m looking at you and your leadership principles Amazon 🤢🥴 lol, jk, kinda). But in all seriousness, you can tell a lot about your alignment to a company and their values based on this page. Additionally, sites like Glassdoor and Blind can provide valuable insights into the company's interview process, employee experiences, and salaries. It's also a good idea to research your interviewer and their role to get a better understanding of their perspective and what they may be looking for in a candidate. After diving into the company values, reflect on whether you really want this job. How has the interview process been so far? Often our instincts are powerful tools that are ignored; it's essential to address any reservations about the role or company before proceeding with the process. Self-reflect throughout the entire process and do it often! Practice, Practice, Practice 🙇‍♀️ Do you have a mentor? There are many reasons why it’s important to have a great mentor, but in this case, it’s ideal for practice. Below are some links to mostly free technical interview resources that could be useful to practice alone and with your mentor. Treat every practice as an interview; it might even help with those game day nerves!&nbsp; Useful (mostly) free technical interview links: Leetcode (practice questions) Pramp (live practice interviews) Algorithm Fundamentals FAANG interview questions (data structures) Cracking the coding interview (I know, I know 🫤) MIT systems design course Book on systems design interviews Quastor (newsletter with a free systems design guidebook) Non-coding technical interview questions: These get incrementally harder 50 questions and answers Generalized interview questions &nbsp; Behavioral interview prep: In the 'Knowledge is Power' section, I mentioned the importance of identifying company values. Once you’ve identified them, create STAR method examples for each of those values. I especially love the STAR method because it allows for precise and example-heavy answers. We’ve seen many candidates eliminated for anything from too concise of answers with no substance to long-winded and rambling replies. Additionally, the STAR method will help you create answers to potential behavioral interview questions. Come up with STAR examples for each bullet in the job description (if there are too many bullets, gather themes). Behavioral interview questions are often taken directly from these job description bullet points. For example: + Strong problem-solving skills, with the ability to think creatively and strategically to solve complex technical challenges -> Tell me about a time you encountered obstacles and challenges at work. How did you overcome? + Ability to communicate cross-functionally and within product, design, and development -> Tell me about a time you had to work with many different stakeholders to complete a project? How did you accomplish this? What were your successes/failures? Furthermore, you can find some sample behavioral interview questions here. Stop, Collaborate and Listen 👂 While finding the perfect technical solution is great, many candidates have failed technical interviews but still landed the job. How? By demonstrating good collaboration skills, explaining their thought processes, and most importantly, their mistakes. If you can articulate your f-ups and \"could-have-beens\" well, you might just get the job. Often, it's more about your approach and your ability to be a good teammate than your solution. During the technical interview, keep these questions in mind: + Have you gathered your requirements? Do you know what you're doing? +Are you checking in with your interviewer? They're there to collaborate with you. +Are you articulating what you're doing? +Are you asking for feedback? + Are you running out of time? Check in. + Are you overwhelmed? Ask for a moment. It's okay to take a break. +Can you scale your solution? If so, how? +Are you over-engineering? Lastly, come prepared with your own questions for the interviewer.&nbsp; Know Yourself, Be Yourself 🥳 Reflect on your strengths, weaknesses, interests, and opportunities for growth. Being honest and vulnerable (when safe) can help you stand out from other candidates. When describing previous employers and roles be sure to keep it positive! Any opportunity (especially negative ones) can teach you a lot about yourself. Remember, you're freaking awesome, and your unique qualities and ",
    "blockText": []
  },
  {
    "file": "bret.html",
    "route": "/bret",
    "label": "Bret",
    "seoTitle": "Find Top Talent with Code Recruitment Solutions USA",
    "seoDescription": "Unlock your career potential with code., a leading U.S. recruitment agency, connecting you with top employers for tailored job opportunities and career growth.",
    "visibleText": "Find Top Talent with Code Recruitment Solutions USA code. Team Meetups About Blog Our Services Bret Smith Email: [email&#160;protected]",
    "blockText": [
      "Bret Smith Email: Bret@code-talent.com"
    ]
  },
  {
    "file": "candidate-intake.html",
    "route": "/candidate-intake",
    "label": "Candidate Intake",
    "seoTitle": "Unlock Success with Professional US Coding Services",
    "seoDescription": "Discover code., a top-notch business in the United States offering innovative tech solutions. Enhance your projects with our expert services for growth and success.",
    "visibleText": "Unlock Success with Professional US Coding Services code. Team Meetups About Blog Our Services Candidate Intake Form",
    "blockText": [
      "Candidate Intake Form",
      ""
    ]
  },
  {
    "file": "candidate.html",
    "route": "/candidate",
    "label": "Candidate",
    "seoTitle": "Expert Software Developers for Innovative Code Solutions",
    "seoDescription": "Discover Code, the leading tech solutions provider in the USA. Our expert team delivers innovative software development, web design, and IT consulting services.",
    "visibleText": "Expert Software Developers for Innovative Code Solutions code. Team Meetups About Blog Our Services Candidate Intake Form",
    "blockText": [
      "Candidate Intake Form",
      ""
    ]
  },
  {
    "file": "conor.html",
    "route": "/conor",
    "label": "Conor",
    "seoTitle": "Discover Top Talent with Code: Leading US Recruiters",
    "seoDescription": "Discover your dream job with code., the leading recruitment agency in the United States. We connect talented professionals with top companies nationwide!",
    "visibleText": "Discover Top Talent with Code: Leading US Recruiters code. Team Meetups About Blog Our Services Conor Swanson Product guy and geek at heart. I love connecting great people and great companies. I'm a co-chair for Denver Startup Week, a Techstars Alum, and the Co-Founder of Three Cents (Product Hunt Winner). Previously, I helped build SafteyWeb, which was acquired by Experian. Amateur Dad and Lucky Husband. Email : [email&#160;protected]",
    "blockText": [
      "Conor Swanson Product guy and geek at heart. I love connecting great people and great companies. I'm a co-chair for Denver Startup Week, a Techstars Alum, and the Co-Founder of Three Cents (Product Hunt Winner). Previously, I helped build SafteyWeb, which was acquired by Experian. Amateur Dad and Lucky Husband. Email : conor@code-talent.com"
    ]
  },
  {
    "file": "contact-us.html",
    "route": "/contact-us",
    "label": "Contact",
    "seoTitle": "Top US Recruitment Solutions for Tech Talent by code.",
    "seoDescription": "Find top talent with code., a leading US recruitment agency. We connect businesses with skilled professionals to drive growth and success. Get started today!",
    "visibleText": "Top US Recruitment Solutions for Tech Talent by code. code. Team Meetups About Blog Our Services Contact Please drop us a line! We'd love to help you: ✅ Find amazing talent for your organization 🧐 Discover your next great position 🏡 Host a meetup or event at our space Name Email Reason for Reaching Out Message Send This site is protected by reCAPTCHA and the Google Privacy Policy and Terms of Service apply . Build Your Dream Team Today Partner with Code, the trusted recruitment experts, to find top talent and drive your business forward. Let us handle the details while you focus on growth. Get Started",
    "blockText": [
      "Please drop us a line! We'd love to help you: ✅ Find amazing talent for your organization 🧐 Discover your next great position 🏡 Host a meetup or event at our space",
      "Partner with Code, the trusted recruitment experts, to find top talent and drive your business forward. Let us handle the details while you focus on growth."
    ]
  },
  {
    "file": "eric.html",
    "route": "/eric",
    "label": "Eric",
    "seoTitle": "Top Talent Recruitment Services in the US by Code.",
    "seoDescription": "Discover top talent with Code Recruitment Agency in the US. We connect businesses with skilled candidates, ensuring the perfect match for your hiring needs.",
    "visibleText": "Top Talent Recruitment Services in the US by Code. code. Team Meetups About Blog Our Services Eric Hernandez Email: [email&#160;protected]",
    "blockText": [
      "Eric Hernandez Email: eric@code-talent.com"
    ]
  },
  {
    "file": "home.html",
    "route": "/",
    "label": "Home",
    "seoTitle": "Code Talent - Building standout teams",
    "seoDescription": "Discover top talent in Denver, CO with code.. Our expert recruitment agency connects you to skilled professionals in tech, ensuring your business thrives.",
    "visibleText": "Code Talent - Building standout teams code. Team Meetups About Blog Our Services Connecting standout people with standout teams. Hire Talent Why Code Connections We work with many outstanding tech companies backed by the top Venture Capitalists and Private Equity firms. Community Code regularly hosts many meet-ups in our space and we actively support Denver Startup Week each year with great events. Competency Our team has built products featured in the App Store and co-founded a Techstars company. We understand technology and the demands of high-growth business. We love our team. Get to Know Us codetechtalent Slide 1 of 5 Code has been instrumental in helping me hire top engineering talent from my startup's earliest stages through various growth phases. The team's extensive network and commitment to long-term relationships make them an invaluable resource for any company looking to develop outstanding teams. Jessica Rusin - CTO at Guild We've hired some of our best engineering talent through Code Talent. My relationship with the team dates back to the early days of our startup, and I couldn’t imagine a better partner Franz Garsombke - CTO at Rachio Code is a fantastic partner. I can always count on them to quickly understand the recruiting requirements and only introduce candidates who meet our expectations - spot-on. Code has helped me build strong, reliable, expert software engineering teams. Michael Kolbrenner - CTO at Promontech Then there are tech recruiters like Conor Swanson (Code)—unbelievably plugged in and deeply invested in knowing everything about everyone’s business, long before they need anything from you. They add value upfront, and they’re who you naturally turn to. You don’t need to explain who you are—there’s already a shorthand because of the relationship. Bryan Leach - CEO and Founder of Ibotta Great teamwork across our companies to find the right candidate for the role. Also, Code Talent does it with the same personal approach that we value as a company. Thanks to you and your team. Aaron Hoffman -VP Engineering at PaymentWorks Code has been instrumental in helping me hire top engineering talent from my startup's earliest stages through various growth phases. The team's extensive network and commitment to long-term relationships make them an invaluable resource for any company looking to develop outstanding teams. Jessica Rusin - CTO at Guild We've hired some of our best engineering talent through Code Talent. My relationship with the team dates back to the early days of our startup, and I couldn’t imagine a better partner Franz Garsombke - CTO at Rachio Code is a fantastic partner. I can always count on them to quickly understand the recruiting requirements and only introduce candidates who meet our expectations - spot-on. Code has helped me build strong, reliable, expert software engineering teams. Michael Kolbrenner - CTO at Promontech Then there are tech recruiters like Conor Swanson (Code)—unbelievably plugged in and deeply invested in knowing everything about everyone’s business, long before they need anything from you. They add value upfront, and they’re who you naturally turn to. You don’t need to explain who you are—there’s already a shorthand because of the relationship. Bryan Leach - CEO and Founder of Ibotta Great teamwork across our companies to find the right candidate for the role. Also, Code Talent does it with the same personal approach that we value as a company. Thanks to you and your team. Aaron Hoffman -VP Engineering at PaymentWorks Code has been instrumental in helping me hire top engineering talent from my startup's earliest stages through various growth phases. The team's extensive network and commitment to long-term relationships make them an invaluable resource for any company looking to develop outstanding teams. Jessica Rusin - CTO at Guild We've hired some of our best engineering talent through Code Talent. My relationship with the team dates back to the early days of our startup, and I couldn’t imagine a better partner Franz Garsombke - CTO at Rachio Code is a fantastic partner. I can always count on them to quickly understand the recruiting requirements and only introduce candidates who meet our expectations - spot-on. Code has helped me build strong, reliable, expert software engineering teams. Michael Kolbrenner - CTO at Promontech Then there are tech recruiters like Conor Swanson (Code)—unbelievably plugged in and deeply invested in knowing everything about everyone’s business, long before they need anything from you. They add value upfront, and they’re who you naturally turn to. You don’t need to explain who you are—there’s already a shorthand because of the relationship. Bryan Leach - CEO and Founder of Ibotta Great teamwork across our companies to find the right candidate for the role. Also, Code Talent does it with the same personal approach that we value as a company. Thanks to you and your team. Aaron Hoffman -VP Engineering at PaymentWorks Reach Out to Our Team Let us know how we can help! Name Email Message Send This site is protected by reCAPTCHA and the Google Privacy Policy and Terms of Service apply .",
    "blockText": [
      "Reach Out to Our Team Let us know how we can help!"
    ]
  },
  {
    "file": "justin.html",
    "route": "/justin",
    "label": "Justin",
    "seoTitle": "Find Top Talent with Code Recruitment Services USA",
    "seoDescription": "Discover top talent with code., a leading U.S. recruitment agency. We specialize in matching skilled professionals with top companies. Elevate your team today!",
    "visibleText": "Find Top Talent with Code Recruitment Services USA code. Team Meetups About Blog Our Services Justin Cosmano Email: [email&#160;protected]",
    "blockText": [
      "Justin Cosmano Email: justin@code-talent.com"
    ]
  },
  {
    "file": "kevin.html",
    "route": "/kevin",
    "label": "Kevin",
    "seoTitle": "Top Recruitment Services for Tech Professionals | Code.",
    "seoDescription": "Discover top-notch talent with code., a leading recruitment agency in the USA. We match skilled professionals with companies to foster growth and innovation.",
    "visibleText": "Top Recruitment Services for Tech Professionals | Code. code. Team Meetups About Blog Our Services Kevin Doran Email : [email&#160;protected]",
    "blockText": [
      "Kevin Doran Email : kevin@code-talent.com"
    ]
  },
  {
    "file": "matt.html",
    "route": "/matt",
    "label": "Matt",
    "seoTitle": "Top Talent Recruitment Services in the USA - Code Agency",
    "seoDescription": "code. Recruitment Agency in the USA offers specialized staffing solutions to match top talent with the best employers. Your search for quality candidates ends here.",
    "visibleText": "Top Talent Recruitment Services in the USA - Code Agency code. Team Meetups About Blog Our Services Matt Moore Email: [email&#160;protected]",
    "blockText": [
      "Matt Moore Email: matt@code-talent.com"
    ]
  },
  {
    "file": "meetups.html",
    "route": "/meetups",
    "label": "Meetups",
    "seoTitle": "Code Meetups Calendar",
    "seoDescription": "Looking for top talent in the US? code. Recruitment Agency connects businesses with skilled professionals, boosting your team with expert recruitment solutions.",
    "visibleText": "Code Meetups Calendar code. Team Meetups About Blog Our Services Community Involvement 🤝 Code Talent was built on giving back. We’ve supported the Colorado tech community since our founding and continue to do so today. If you're looking for a space to host a meetup or event please contact us ! Meetups and events we've supported: 🔩 AI Tinkerers 💡 Black Tech Denver 📲 CocoaHeads Denver 🌲 Colorado Product Foundation 🖲️ Denver Data Engineers 🤖 Denver DevOps 🧪 Denver Elixir Meetup ↗️ Denver Leadership Meetup ⚙️ Denver Microservices Meetup 🐍 Denver Python Meetup ☀️ Denverscript Meetup 🏔️ Denver Startup Week 📝 HighView Sessions 🚀 MLOps Meetup 🐿️ Mile High Gophers (Golang Meetup) 👀 Paired Community 🔥 React Meetup 💻 The R Meetup ✅ Test Tribe QA Meetup 💁‍♀️ Women in Product 🌁 Vue Meetup And more!",
    "blockText": [
      "",
      "Community Involvement 🤝 Code Talent was built on giving back. We’ve supported the Colorado tech community since our founding and continue to do so today. If you're looking for a space to host a meetup or event please contact us ! Meetups and events we've supported: 🔩 AI Tinkerers 💡 Black Tech Denver 📲 CocoaHeads Denver 🌲 Colorado Product Foundation 🖲️ Denver Data Engineers 🤖 Denver DevOps 🧪 Denver Elixir Meetup ↗️ Denver Leadership Meetup ⚙️ Denver Microservices Meetup 🐍 Denver Python Meetup ☀️ Denverscript Meetup 🏔️ Denver Startup Week 📝 HighView Sessions 🚀 MLOps Meetup 🐿️ Mile High Gophers (Golang Meetup) 👀 Paired Community 🔥 React Meetup 💻 The R Meetup ✅ Test Tribe QA Meetup 💁‍♀️ Women in Product 🌁 Vue Meetup And more!"
    ]
  },
  {
    "file": "nick.html",
    "route": "/nick",
    "label": "Nick",
    "seoTitle": "Discover Top Talent with Code: Your US Recruitment Partner",
    "seoDescription": "Code Recruitment: Connecting top talent with leading businesses across the US. Discover your next career opportunity or find the perfect candidate today!",
    "visibleText": "Discover Top Talent with Code: Your US Recruitment Partner code. Team Meetups About Blog Our Services Nick Gasparro Email : [email&#160;protected]",
    "blockText": [
      "Nick Gasparro Email : nick@code-talent.com"
    ]
  },
  {
    "file": "privacy-policy.html",
    "route": "/privacy-policy",
    "label": "Privacy Policy",
    "seoTitle": "U.S. CodeRecruit: Top Talent Connections Made Easy",
    "seoDescription": "Connect with top talent and leading employers in the United States with code. recruitment agency. Elevate your hiring strategy and career growth today.",
    "visibleText": "U.S. CodeRecruit: Top Talent Connections Made Easy code. Team Meetups About Blog Our Services Privacy Policy Updated Nov 27, 2023 At Code we take your privacy seriously and would like to describe how we collect, use and protect your information when you access our website(s), products, services and applications (collectively, the “Services”). What does this Privacy Policy cover? This Privacy Policy covers our treatment of personally identifiable information (“Personal Information”) that we gather when you are accessing or using our Services. We gather various types of Personal Information from our users, as explained in more detail below, and we use this Personal Information in order to make our Services available to you, to contact you, and to better understand how you use the Services. In certain cases, we may also share some Personal Information with third parties, but only as described below. We do not knowingly collect or solicit personal information from anyone under the age of 16. If you are under 16, please do not attempt to register for the Services or send any personal information about yourself to us. If we learn that we have collected personal information from a child under age 16, we will delete that information as quickly as possible. If you believe that a child under 16 may have provided us personal information, please contact us at [email&#160;protected] Will Code ever change this Privacy Policy? We’re constantly trying to improve our Services, so we may need to change this Privacy Policy from time to time as well, but if we do, we will bring it to your attention by placing a notice in the Code website and/or by sending you an email, and/or by some other means. Your use of the Services after any changes to the Privacy Policy have been posted will be considered to indicate your acceptance of the changes. What Information does Code Collect? Information You Provide to Us We collect Personal Information you submit to us, for example by completing a form on www.code-talent.com/contact-us. In that case, we may communicate with you, for example by calling you at the phone number you provide, sending you promotional email offers, or emailing you about your use of the Services. Also, we may receive a confirmation when you open an email from us. This confirmation helps enhance our engagement with you and generally improve our Services. If you do not want to receive communications from us, please indicate your preference by sending an email to [email&#160;protected] . Information Collected From Other Websites and Do Not Track Policy Through cookies we place on your browser or device, we may collect information about your online activity after you leave our Services. Just like any other usage information we collect, this information allows us to improve the Services and customize your online experience. Your browser may offer you a “Do Not Track” option, which allows you to signal to operators of websites and web applications and services (including behavioral advertising services) that you do not wish such operators to track certain of your online activities over time and across different websites. Our Services do not support Do Not Track requests at this time, which means that we may collect information about your online activity both while you are using the Services and after you leave our Services. Do Not Track signals are set on a browser-by-browser basis, so you must set them on every browser you use if you do not wish to be tracked. Third Party Analytics Services We use third party analytics services in order to better understand user engagement with the Services. When a user browses or uses the Services, these third party analytics services may collect the user’s IP address, browser type, and approximate location (based on the IP address). They may also use web logs or web beacons and may set and access cookies on your computer or other device. Does Code Share Personal Information? We neither rent nor sell your Personal Information to anyone. However, we may share your Personal Information with third parties as described in this section: Agents and vendors: We employ other companies and people to perform tasks on our behalf and need to share your information with them, including in some cases the Personal Information you have provided to us, in order to make the Services available to you. For example, we may use third party hosting providers or software developers to help implement and maintain the Services. However, our agents do not have any right to use the Personal Information we share with them beyond what is necessary to assist us. Business Transfers: If we are involved in a reorganization, merger, acquisition or sale of our assets, your information may be transferred as part of that deal. We will notify you (for example, via a message to the email address associated with your account) of any such deal and outline your choices in that event. Protection of Code and Others: We reserve the right to access, read, preserve, and disclose any information that we believe is necessary to comply with law or court order; enforce or apply our applicable terms of use and other agreements; or protect the rights, property, or safety of Code, our employees, our users, or others. Is Personal Information about me secure? We will use very diligent efforts to protect the privacy of your account and other Personal Information we hold in our records, but unfortunately, we cannot guarantee complete security. Unauthorized entry or use, hardware or software failure, and other factors, may compromise the security of user information at any time. What Personal Information can I access? You can email [email&#160;protected] for access to, or to update or delete, your Personal Information that Code has collected. Transfer to the U.S. or Other Countries We currently use datacenter facilities located exclusively in the United States. Your information will be storecd and processed in the United States ",
    "blockText": [
      "Privacy Policy Updated Nov 27, 2023 At Code we take your privacy seriously and would like to describe how we collect, use and protect your information when you access our website(s), products, services and applications (collectively, the “Services”). What does this Privacy Policy cover? This Privacy Policy covers our treatment of personally identifiable information (“Personal Information”) that we gather when you are accessing or using our Services. We gather various types of Personal Information from our users, as explained in more detail below, and we use this Personal Information in order to make our Services available to you, to contact you, and to better understand how you use the Services. In certain cases, we may also share some Personal Information with third parties, but only as described below. We do not knowingly collect or solicit personal information from anyone under the age of 16. If you are under 16, please do not attempt to register for the Services or send any personal information about yourself to us. If we learn that we have collected personal information from a child under age 16, we will delete that information as quickly as possible. If you believe that a child under 16 may have provided us personal information, please contact us at support@code-talent.com Will Code ever change this Privacy Policy? We’re constantly trying to improve our Services, so we may need to change this Privacy Policy from time to time as well, but if we do, we will bring it to your attention by placing a notice in the Code website and/or by sending you an email, and/or by some other means. Your use of the Services after any changes to the Privacy Policy have been posted will be considered to indicate your acceptance of the changes. What Information does Code Collect? Information You Provide to Us We collect Personal Information you submit to us, for example by completing a form on www.code-talent.com/contact-us. In that case, we may communicate with you, for example by calling you at the phone number you provide, sending you promotional email offers, or emailing you about your use of the Services. Also, we may receive a confirmation when you open an email from us. This confirmation helps enhance our engagement with you and generally improve our Services. If you do not want to receive communications from us, please indicate your preference by sending an email to support@code-talent.com. Information Collected From Other Websites and Do Not Track Policy Through cookies we place on your browser or device, we may collect information about your online activity after you leave our Services. Just like any other usage information we collect, this information allows us to improve the Services and customize your online experience. Your browser may offer you a “Do Not Track” option, which allows you to signal to operators of websites and web applications and services (including behavioral advertising services) that you do not wish such operators to track certain of your online activities over time and across different websites. Our Services do not support Do Not Track requests at this time, which means that we may collect information about your online activity both while you are using the Services and after you leave our Services. Do Not Track signals are set on a browser-by-browser basis, so you must set them on every browser you use if you do not wish to be tracked. Third Party Analytics Services We use third party analytics services in order to better understand user engagement with the Services. When a user browses or uses the Services, these third party analytics services may collect the user’s IP address, browser type, and approximate location (based on the IP address). They may also use web logs or web beacons and may set and access cookies on your computer or other device. Does Code Share Personal Information? We neither rent nor sell your Personal Information to anyone. However, we may share your Personal Information with third parties as described in this section: Agents and vendors: We employ other companies and people to perform tasks on our behalf and need to share your information with them, including in some cases the Personal Information you have provided to us, in order to make the Services available to you. For example, we may use third party hosting providers or software developers to help implement and maintain the Services. However, our agents do not have any right to use the Personal Information we share with them beyond what is necessary to assist us. Business Transfers: If we are involved in a reorganization, merger, acquisition or sale of our assets, your information may be transferred as part of that deal. We will notify you (for example, via a message to the email address associated with your account) of any such deal and outline your choices in that event. Protection of Code and Others: We reserve the right to access, read, preserve, and disclose any information that we believe is necessary to comply with law or court order; enforce or apply our applicable terms of use and other agreements; or protect the rights, property, or safety of Code, our employees, our users, or others. Is Personal Information about me secure? We will use very diligent efforts to protect the privacy of your account and other Personal Information we hold in our records, but unfortunately, we cannot guarantee complete security. Unauthorized entry or use, hardware or software failure, and other factors, may compromise the security of user information at any time. What Personal Information can I access? You can email support@code-talent.com for access to, or to update or delete, your Personal Information that Code has collected. Transfer to the U.S. or Other Countries We currently use datacenter facilities located exclusively in the United States. Your information will be storecd and processed in the United States or other countries where we decide to maintain datacenter facilities in the future. By using the Services, you consent to the transfer of information outside of your country, even if your country has more rigorous data protection standards. What if I have questions about this policy? If you have any questions or concerns regarding our privacy policies, please don’t hesitate to contact us at support@code-talent.com and we will try to resolve your concerns. We’re constantly trying to improve our Services, so we may need to change this Privacy Policy from time to time as well, but if we do, we will bring it to your attention by placing a notice in the Code website and/or by sending you an email, and/or by some other means. Your use of the Services after any changes to the Privacy Policy have been posted will be considered to indicate your acceptance of the changes. What Information does Code Collect? Information You Provide to Us We collect Personal Information you submit to us, for example by completing a form on www.code-talent.com/contact-us. In that case, we may communicate with you, for example by calling you at the phone number you provide, sending you promotional email offers, or emailing you about your use of the Services. Also, we may receive a confirmation when you open an email from us. This confirmation helps enhance our engagement with you and generally improve our Services. If you do not want to receive communications from us, please indicate your preference by sending an email to support@code-talent.com. Information Collected From Other Websites and Do Not Track Policy Through cookies we place on your browser or device, we may collect information about your online activity after you leave our Services. Just like any other usage information we collect, this information allows us to improve the Services and customize your online experience. Your browser may offer you a “Do Not Track” option, which allows you to signal to operators of websites and web applications and services (including behavioral advertising services) that you do not wish such operators to track certain of your online activities over time and across different websites. Our Services do not support Do Not Track requests at this time, which means that we may collect information about your online activity both while you are using the Services and after you leave our Services. Do Not Track signals are set on a browser-by-browser basis, so you must set them on every browser you use if you do not wish to be tracked. Third Party Analytics Services We use third party analytics services in order to better understand user engagement with the Services. When a user browses or uses the Services, these third party analytics services may collect the user’s IP address, browser type, and approximate location (based on the IP address). They may also use web logs or web beacons and may set and access cookies on your computer or other device. Does Code Share Personal Information? We neither rent nor sell your Personal Information to anyone. However, we may share your Personal Information with third parties as described in this section: Agents and vendors: We employ other companies and people to perform tasks on our behalf and need to share your information with them, including in some cases the Personal Information you have provided to us, in order to make the Services available to you. For example, we may use third party hosting providers or software developers to help implement and maintain the Services. However, our agents do not have any right to use the Personal Information we share with them beyond what is necessary to assist us. Business Transfers: If we are involved in a reorganization, merger, acquisition or sale of our assets, your information may be transferred as part of that deal. We will notify you (for example, via a message to the email address associated with your account) of any such deal and outline your choices in that event. Protection of Code and Others: We reserve the right to access, read, preserve, and disclose any information that we believe is necessary to comply with law or court order; enforce or apply our applicable terms of use and other agreements; or protect the rights, property, or safety of Code, our employees, our users, or others. Is Personal Information about me secure? We will use very diligent efforts to protect the privacy of your account and other Personal Information we hold in our records, but unfortunately, we cannot guarantee complete security. Unauthorized entry or use, hardware or software failure, and other factors, may compromise the security of user information at any time. What Personal Information can I access? You can email support@code-talent.com for access to, or to update or delete, your Personal Information that Code has collected. Transfer to the U.S. or Other Countries We currently use datacenter facilities located exclusively in the United States. Your information will be storecd and processed in the United States or other countries where we decide to maintain datacenter facilities in the future. By using the Services, you consent to the transfer of information outside of your country, even if your country has more rigorous data protection standards. What if I have questions about this policy? If you have any questions or concerns regarding our privacy policies, please don’t hesitate to contact us at support@code-talent.com and we will try to resolve your concerns."
    ]
  },
  {
    "file": "riley.html",
    "route": "/riley",
    "label": "Riley",
    "seoTitle": "Find Top Talent with Code: Leading US Recruitment Agency",
    "seoDescription": "Discover top talent with code., a leading recruitment agency in the USA. We specialize in tech and IT roles, connecting businesses with skilled professionals.",
    "visibleText": "Find Top Talent with Code: Leading US Recruitment Agency code. Team Meetups About Blog Our Services Riley Newman Email: [email&#160;protected]",
    "blockText": [
      "Riley Newman Email: riley@code-talent.com"
    ]
  },
  {
    "file": "rita.html",
    "route": "/rita",
    "label": "Rita",
    "seoTitle": "Top Recruitment Solutions by Code for US Businesses",
    "seoDescription": "Code. is a leading recruitment agency in the United States, connecting top talent with the best employers in tech, finance, healthcare, and more. Get hired today!",
    "visibleText": "Top Recruitment Solutions by Code for US Businesses code. Team Meetups About Blog Our Services Rita Povlich Email: [email&#160;protected]",
    "blockText": [
      "Rita Povlich Email: rita@code-talent.com"
    ]
  },
  {
    "file": "services.html",
    "route": "/services",
    "label": "Our Services",
    "seoTitle": "Recruitment Solutions for Tech Talent in the U.S. | code.",
    "seoDescription": "Boost your career with code. Recruitment Agency in the United States. Find top-notch job opportunities and talent with our expert staffing solutions. Connect now!",
    "visibleText": "Recruitment Solutions for Tech Talent in the U.S. | code. code. Team Meetups About Blog Our Services Services Get in touch Recruiting Services at Code At Code, we connect top-tier talent with startups and growing tech teams across the country. Whether you’re building out your first engineering squad or hiring your next executive leader, we’ve got flexible recruiting options to match your needs: 1. Contingency-Based Hiring Only pay when you hire. Perfect for fast-growing teams that need quality candidates without upfront costs. 2. Executive Search Targeted, discreet, and high-impact. We specialize in placing senior and executive leaders who can shape your company’s future. 3. Contract-to-Hire Services Try before you commit. This option allows you to bring someone on board with the flexibility to hire full-time later. 4. Contract Services Need short-term or project-based support? We’ll help you find experienced engineers and product talent ready to hit the ground running. Let us know what you're building — and we’ll help you find the right people to build it with. 👉 Contact us to get started Find Top Talent Today Partner with our experts to connect with highly skilled professionals tailored to your organization's unique staffing needs. Experience streamlined hiring processes and exceptional candidate matches now. Hire Now",
    "blockText": [
      "Recruiting Services at Code At Code, we connect top-tier talent with startups and growing tech teams across the country. Whether you’re building out your first engineering squad or hiring your next executive leader, we’ve got flexible recruiting options to match your needs: 1. Contingency-Based Hiring Only pay when you hire. Perfect for fast-growing teams that need quality candidates without upfront costs. 2. Executive Search Targeted, discreet, and high-impact. We specialize in placing senior and executive leaders who can shape your company’s future. 3. Contract-to-Hire Services Try before you commit. This option allows you to bring someone on board with the flexibility to hire full-time later. 4. Contract Services Need short-term or project-based support? We’ll help you find experienced engineers and product talent ready to hit the ground running. Let us know what you're building — and we’ll help you find the right people to build it with. 👉 Contact us to get started",
      "Partner with our experts to connect with highly skilled professionals tailored to your organization's unique staffing needs. Experience streamlined hiring processes and exceptional candidate matches now."
    ]
  },
  {
    "file": "sisson.html",
    "route": "/sisson",
    "label": "Sisson",
    "seoTitle": "Find Top Talent for Your Business with Code Recruitment",
    "seoDescription": "Connect with top talent through code., the leading recruitment agency in the US. We match exceptional candidates with businesses to drive success and growth.",
    "visibleText": "Find Top Talent for Your Business with Code Recruitment code. Team Meetups About Blog Our Services Nick Sisson Email: [email&#160;protected]",
    "blockText": [
      "Nick Sisson Email: nsisson@code-talent.com"
    ]
  },
  {
    "file": "team.html",
    "route": "/team",
    "label": "Team",
    "seoTitle": "Top Talent Solutions for Businesses | Code Recruitment",
    "seoDescription": "Unlock your potential with code. Recruitment Agency. Connecting top talent with exceptional opportunities in the United States. Start your journey to success today!",
    "visibleText": "Top Talent Solutions for Businesses | Code Recruitment code. Team Meetups About Blog Our Services Meet Team Code Rita Povlich Senior Recruiter Contact Heidi Harvey Associate Recruiter Contact Nick Sisson Senior Recruiter Contact Justin Cosmano Senior Recruiter Contact Riley Scardina Principal Recruiter Contact Bret Smith Principal Recruiter Contact Nick Gasparro Co-Founder Contact Eric Hernandez Co-Founder Contact Kevin Doran Co-Founder Contact Conor Swanson Co-Owner Contact",
    "blockText": []
  }
]